Workbook

Sheet Canvas
A1: PARCERIAS | B1: ATIVIDADES-CHAVE | C1: PROPOSTA DE VALOR | D1: RELACIONAMENTOS COM CLIENTES | E1: SEGMENTOS DE CLIENTES
A2: Sócios, no risco: | B2: · Teste manual com 3 empresas
A3: · Desenvolvedor, TI | B3: · Desenvolvimento estrutura | C3: ü Avaliar a situação econômico-financeira de empresas, via internet, automatizada; | D3: · Autosserviço interativo via internet | E3: MEI, Micro e Pequenas Empresas
A4: · Vendas, Marketing | B4: · Banco de dados | C4: ü Contribuir para melhoria de decisões e otimizar resultados; | D4: · Cliente digita as informações (conforme lista de ENTRADA DE DADOS)
B5: · Fórmulas para indicadores | D5: · Sistema emite relatório
B6: · Indexação relatório recomendações | C6: VANTAGEM COMPETITIVA:
B7: · prototipagem | C7: ü Atendimento específico de necessidades de empresários;
B8: · MVP: Validação da plataforma | C8: ü Fácil operacionalização;
B9: · Página inicial | C9: ü Navegação rápida;
B10: · Estratégia de marketing | C10: ü Simplicidade;
B11: · Produção mídia | C11: ü Segurança;
B12: · Entrada de Dados (cliente) | C12: ü Uso intuitivo;
B13: · Tratamento das informações e Emissão de Relatório | C13: ü Responsivo
B14: · Registro, Hospedagem, INPI
B15: · Suporte técnico
B16: · Atualização da plataforma
B17: · Monitoramento
B19: RECURSOS-CHAVE | D19: CANAIS
B20: · Desenvolvimento sistema web | D20: Tráfego pago, Google ads
B21: · Marketing | D21: Instagram, Facebook, Twiter, Youtube, linkedin, whats app
B22: · SEO: Otimização para motores busca
A24: ESTRUTURA DE CUSTOS | D24: FONTES DE RECEITAS
A25: • Desenvolvimento R$ • Registro, Domínio, Hospedagem, VPS,SSL, Provedor, Banco de dados, Nuvem R$ • Teste, MVP, validação, marketing, divulgação na mídia e redes sociais R$ • Manutenção, Suporte: mensal R$ | D25: R$ assinatura anual Ou Grátis, se houver convênio/patrocínio: Sebrae, BB, CNC, CNI, BNB, CDL, Federações

Sheet Insights
A1: INSIGHTS E DESAFIOS | B1: OBSERVAÇÕES E ENCAMINHAMENTOS
A2: Quantidade de CNPJ existentes no país | B2: MDIC, Set/23: 21 milhões
A3: Quantidade de MEI existentes no país | B3: RFB, Set/23: 15 milhões IBGE, 2021: 13 milhões = 69% do total; 50% serviços, 29%o ficinas
A4: Quantidade de micro empresas existentes no país | B4: SEBRAE, 2023: 6 milhões de MPE
A5: Quantidade de pequenas empresas existentes no país | B5: Menos de 1 milhão
A6: Estimativa quantitativa de micro e pequenas empresas como público-alvo?
A7: Metas evolluta de assinantes?
A8: Esse público tem pouca orientação sobre a importância desse tipo de informação para o negócio
A9: Há dificuldade de contadores cobrarem honorário justo pelos serviços contábeis obrigatórios
A10: Plataforma com informações consistentes
A11: Público-alvo precisa compreender a importância do DEF on line
A12: Há pessoas que sabem da importância mas não valorizam
A13: Acredito seria utilizado sim. Inicialmente, pelo menos. Hoje se testa aplicativo diariamente, mas também são descartados na mesma velocidade se não atendem à expectativa do usuário
A14: Se não custar muito caro produzir e disponibilizar para os usuários, pode valer a pena testar a viabilidade de oferecer serviços a partir do app
A15: A empresa precisa ficar consultando o aplicativo em quando tempo em média?
A16: Como é que clientes tomam conhecimento do DEF on line e chegam ao produto?
A17: Declaração do atual cenário do projeto Início dos levantamentos do problema, oportunidade e/ou desafio que darão origem ao projetos pontos declarados e apresentados por agentes envolvidos foram postos de maneira clara e realista utilize ferramentas como: Análise de SWOT ou Realização de Workshop para explorar melhor o problema.
... A28: ideia precisa atrair o interesse e a atenção
A29: suporte de especialista em finanças para esclarecer dúvidas por email | B29: eb@ebparcerias.com
A30: a responsabilidade pela qualidade das informações alimentadas na Entrada de Dados é do usuário assinante, esclarecido que a assertividade e análise técnica depende da coerência dos dados digitados | B30: assinalamento pelo assinante
A31: estrutura aberta para permitir, em novas versões, a integração com TEF, por exemplo, dashboard, gráficos etc
A32: produto inédito, único
A33: qual o problema o DEF on line vai resolver
A34: escolher pessoas para apontar pontos cegos do produto
A35: experiência do usuário
A36: nenhum usuário vai pagar mais do que o valor que percebe
A37: armazenamento em nuvem
A38: saber se os MEI, Micro e Pequenos empresários tê interesse no APP DEF on line
A39: definir problema/oportunidade
A40: criar protótipo
A41: testar protótipo
A42: congregar afiliados para divulgação com comissão
... A78: Antecipação a problemas; Acompanhamento efetivo do desempenho do negócio; Identificação tempestiva e preventiva de anomalias;
A79: PROPOSTA DE VALOR: Avaliar a situação econômico-financeira do negócio, via APP ou site | B79: https://analistamodelosdenegocios.com.br/canvas-da-proposta-de-valor/
A80: Fácil operacionalização; Navegação rápida; Simplicidade; Segurança; Uso intuitivo; Responsivo
A81: Opção para imprimir ou salvar em pdf o Relatório com indicadores e recomendações técnicas em linguagem amigável, objetiva e clara
A82: cronograma de desenvolvimento da estrutura básica do MVP (APP IOS/Android e site)
A83: acesso do usuário para alimentar a entrada de dados somente após cadastro login (CPNJ/CPF, email, senha) e conferência do pagamento da assinatura, no prazo de validadde (até 12 meses após a data do pagamento)
A84: estratégias de divulgação em redes sociais
A85: Testar a ideia
A86: plano de contingência
A87: quais as melhores formas de se chegar ao cliente
A88: é preciso pensar em formas de incentivar que o produto seja conhecido amplamente e consumido
A89: versões em português, espanhol, inglês e francês
A90: necessidade reconhecida pelo mercado
A91: posicionar protótipo na mente do consumidor
... A105: Transparência, segurança da informação, LGPD

Sheet Ações
A1: DATA | B1: AÇÃO | C1: RESPONSÁVEL | D1: INTERVENIENTE | E1: FOLLOW UP | F1: STATUS | G1: ENCAMINHAMENTOS
A2: 45224 | B2: Firmar NDA sobre DEF on line | C2: Alex | D2: EBC | E2: 45247 | F2: DONE | G2: Termo assinado em 17-11-2023
A3: 45247 | B3: Confirmar interesse na sociedade e no risco desenvolver MVP, assumir TI | C3: Alex | E3: 45252 | F3: DONE
A4: 45252 | B4: Sondar potencial parceiro que assuma MKT/comercial, no risco | C4: Alex | E4: 45319 | F4: DOING
A5: 45252 | B5: Sondar potencial parceiro que assuma MKT/comercial, no risco | C5: EBJ | D5: EBC | E5: 45319 | F5: DOING
A6: 45252 | B6: Consultar alguns contadores sobre a efetiva necessidade do produto por parte dos micro e pequenos empresários | C6: EBC | E6: 45266 | F6: DOING | G6: recebendo opiniões, questionamentos e teste (Bernardo, Paulo Vizeu, Paula, Ana Gurgel, Danilo Brito, Demotier, Eliésio, José Augusto, Josenilton, Damacena, Sidney e outros 40 )
A7: 45255 | B7: Elaborar cronograma do desenvolvimento do MPV do APP/site | C7: Alex | E7: 45319 | F7: TO DO
A8: 45259 | B8: Desenvolver MoCap | C8: Alex | E8: 45342 | F8: TO DO
A9: 45252 | B9: Compartilhar minutas básicas do modelo de negócios, estrutura, entrada de dados, relatório, contrato de parceria e assinatura por usuários | C9: EBC | D9: Alex e EBJ | E9: 45275 | F9: DONE | G9: Enviado para análise por Alex e EBJ
A10: 45252 | B10: Análise minutas: modelo de negócios, estrutura, entrada de dados, relatório, contrato de parceria e assinatura por usuários | C10: Alex | D10: EBJ | E10: 45319 | F10: DOING

Sheet Entrada de dados
A1: CNPJ ou/CPF
A2: Setor de atuação (Indústria, Comércio, Serviços?)
A3: E-mail
A4: Disponibilidades em caixa, bancos, aplicações (o total, nesta data, independente do prazo)
A5: Montate das duplicatas, cheques e cartão de crédito a receber (R$ mil), (o total, nesta data, independente do prazo)
A6: Valor do estoque nesta data (R$ mil)
A7: Valor venal de mercado estimado dos imóveis, equipamentos e veículos (R$ mil)
A8: Saldo devedor dos empréstimos, financiamentos e outras Dívidas a pagar (R$ mil), (o total, nesta data, independente do prazo)
A9: Débitos com fornecedores (R$ mil), (o total, nesta data, independente do prazo)
A10: Valor médio mensal das compras realizadas nos últimos 12 meses (R$ mil)
A11: Valor médio mensal das vendas realizadas nos últimos 12 meses (R$ mil)
A12: Prazo médio de pagamento das compras: (dias):
... A21: ( ) Quero receber mailing da EB Parcerias

Sheet Relatório
A1: CNPJ ou CPF | B1: ='Entrada de dados'!B1 -> 0
A2: Setor de atuação | B2: ='Entrada de dados'!B2 -> 0
A3: EMAIL | B3: ='Entrada de dados'!B3 -> 0
A4: RAZÃO SOCIAL | B4: API de consulta dados públicos na RFB, a partir do CNPJ
A5: NOME FANTASIA | B5: "
A6: DATA FUNDAÇÃO | B6: "
A7: CNAE PRINCIPAL | B7: "
A8: MUNICÍPIO | B8: "
A9: UF | B9: "
A10: SITUAÇÃO | B10: "
A12: BALANÇO E DRE ADAPTADOS | B12: (o balanço não precisa ser mostrado no relatório) | C12: campos hachurados não são mostrados
A13: Disponibilidades | B13: ='Entrada de dados'!B4 -> 0
A14: ACF | B14: =B13 -> 0
A15: Clientes | B15: ='Entrada de dados'!B5 -> 0
A16: Estoques | B16: ='Entrada de dados'!B6 -> 0
A17: ACC | B17: =B15+B16 -> 0
A18: AC | B18: =B14+B17 -> 0
A19: Imobilizado | B19: ='Entrada de dados'!B7 -> 0
A20: ANC | B20: =B19 -> 0
A21: Ativo | B21: =B18+B20 -> 0
A22: Empréstimos | B22: ='Entrada de dados'!B8 -> 0
A23: PCF | B23: =B22 -> 0
A24: Fornecedores | B24: ='Entrada de dados'!B9 -> 0
A25: PCC | B25: =B24 -> 0
A26: PC | B26: =B23+B25 -> 0
A27: PL | B27: =B21-B26 -> 0
A28: Passivo | B28: =B26+B27 -> 0
A29: Vendas (ROB, ROL) | B29: ='Entrada de dados'!B11 -> 0
A30: Compras (CPF, CMV, CSV) | B30: ='Entrada de dados'!B10 -> 0
A31: Lucro Bruto (MB) | B31: =B29-B30 -> 0
A32: Despesas fixas | B32: ='Entrada de dados'!B16 -> 0
A33: Despesas variáveis | B33: ='Entrada de dados'!B17 -> 0
A34: Lucro Operacional (Ebitda) | B34: =B31-B32-B33 -> 0
A35: Despesas financeiras | B35: ='Entrada de dados'!B18 -> 0
A36: Lucro Operacional Líquido (MOL) | B36: =B34-B35 -> 0
A37: Indicadores | B37: Fórmula | C37: Situação em DDMMAAAA, APP assume automaticamente data/hora preenchimento Entrada de Dados | D37: QUANTO MAIOR
A38: Margem Bruta | B38: lucro bruto / vendas * 100 | C38: =B31/B29*100 -> #DIV/0! | D38: MELHOR
A39: Margem Operacional (EBITDA): mede a eficiência em produzir lucros por meio das vendas | B39: Lucro operacional antes IR e Desp Fin / ROL * 100 | C39: =B34/B29*100 -> #DIV/0! | D39: MELHOR
A40: Margem Operacional Líquida (MOL): parcela operacional de lucro obtida sobre as vendas | B40: LOL / ROL * 100 | C40: =B36/B29*100 -> #DIV/0! | D40: MELHOR
A41: Relação Dívida Líquida / Ebitda: demonstra o número de períodos que uma empresa levaria para pagar sua dívida líquida | B41: ( (PCF+Fin.LP) -ACF) / Ebitda | C41: =(B23-B14)/B34 -> #DIV/0! | D41: PIOR
A42: Relação Despesas Financeiras e Ebitda: representa a participação dos bancos no lucro | B42: Despesas Financeiras / LO * 100 | C42: =B35/B34*100 -> #DIV/0! | D42: PIOR
A43: Relação entre as Fontes de Recursos – RFR: quanto a empresa possui de recursos de terceiros para cada unidade do capital próprio, retrata a dependência de recursos externos | B43: (PC + ELP + REF) / PL | C43: =B26/B27 -> #DIV/0! | D43: PIOR
A44: Giro do Ativo (GA): quantas vezes girou o ativo da empresa durante o período | B44: 2 x ROL / Ativo total médio | C44: =B29*2/B28 -> #DIV/0! | D44: MELHOR
A45: Ciclo Financeiro (CF): necessidade de financiamento complementar do capital de giro, em número de dias, em média | B45: PME + PMR – PMC | C45: ='Entrada de dados'!B13+'Entrada de dados'!B14-'Entrada de dados'!B12 -> 0 | D45: PIOR
A46: Necessidade de Capital de Giro (NCG) | B46: Estoques + Clientes - Fornecedores | C46: =B15+B16-B24 -> 0 | D46: MAIS PRECISA DE CAPITAIS DE TERCEIROS
A47: Relação NCG/Vendas | B47: (ACC-PCC)/ROB | C47: =(B17-B25)/B29 -> #DIV/0! | D47: PIOR
A49: INDICADOR | B49: se INDÚSTRIA | C49: RECOMENDAÇÕES (Indústria) | D49: se COMÉRCIO | E49: RECOMENDAÇÕES (Comércio) | F49: se SERVIÇO | G49: RECOMENDAÇÕES (Serviço)
A50: Margem Bruta | B50: Até 10% | C50: Reduzir custos nas compras, não confundir faturamento com lucro, ampliar a carteira de clientes e a participação no mercado, identificar produtos com menor margem de contribuição para zerar o estoque dos mesmos e focar naqueles com maior margem | D50: Até 15% | E50: Reduzir custos nas compras, não confundir faturamento com lucro, ampliar a carteira de clientes e a participação no mercado, identificar produtos com menor margem de contribuição para zerar o estoque dos mesmos e focar naqueles com maior margem | F50: Até 20% | G50: Reduzir custos nas compras, não confundir faturamento com lucro, ampliar a carteira de clientes e a participação no mercado, identificar produtos com menor margem de contribuição e focar naqueles com maior margem
B51: Entre 11 e 20% | C51: Revisar e acompanhar os custos,apurar as margens de contribuição dos itens mais representativos, aumentar a participação no mercado e ampliar a carteira de clientes | D51: Entre 15 e 25% | E51: Revisar e acompanhar os custos,apurar as margens de contribuição dos itens mais representativos, aumentar a participação no mercado e ampliar a carteira de clientes | F51: Entre 21 e 30% | G51: Revisar e acompanhar os custos,apurar as margens de contribuição dos itens mais representativos, aumentar a participação no mercado e ampliar a carteira de clientes
B52: Acima de 20% | C52: Acompanhar os números para manter a margem atual com melhoria contínua | D52: Acima de 25% | E52: Acompanhar os números para manter a margem atual com melhoria contínua | F52: Acima de 30% | G52: Acompanhar os números para manter a margem atual com melhoria contínua
A54: Margem Operacional (EBTIDA) | B54: Até 8% | C54: Enxugar estruturas, reduzir custos e despesas, ampliar a carteira de clientes e a participação no mercado, estabelecer módica retirada para os sócios (pró-labore), não confundir Faturamento com Lucro nem misturar o "caixa do negócio" com o "bolso do dono" | D54: Até 5% | E54: Enxugar estruturas, reduzir custos e despesas, ampliar a carteira de clientes e a participação no mercado, estabelecer módica retirada para os sócios (pró-labore), não confundir Faturamento com Lucro nem misturar o "caixa do negócio" com o "bolso do dono" | F54: Até 10% | G54: Enxugar estruturas, reduzir custos e despesas, ampliar a carteira de clientes e a participação no mercado, estabelecer módica retirada para os sócios (pró-labore), não confundir Faturamento com Lucro nem misturar o "caixa do negócio" com o "bolso do dono"
B55: Entre 8 e 12% | C55: Revisar estruturas para identificar necessidade de enxugamento, revisar e acompanhar custos e despesas, principalmente os fixos | D55: Entre 5 e 10% | E55: Revisar estruturas para identificar necessidade de enxugamento, revisar e acompanhar custos e despesas, principalmente os fixos | F55: Entre 10 e 15% | G55: Revisar estruturas para identificar necessidade de enxugamento, revisar e acompanhar custos e despesas, principalmente os fixos
B56: Acima de 12% | C56: Acompanhar os números para melhorar a margem atual | D56: Acima de 10% | E56: Acompanhar os números para melhorar a margem atual | F56: Acima de 15% | G56: Acompanhar os números para melhorar a margem atual
A58: Margem Operacional Líquida (MOL) | B58: Até 5% | C58: Enxugar estruturas e reduzir custos e despesas, não confundir faturamento com lucro, não misturar o "caixa do negócio" com o "bolso do dono", estabelecer módica retirada para os sócios (pró-labore) | D58: Até 3% | E58: Enxugar estruturas e reduzir custos e despesas, não confundir faturamento com lucro, não misturar o "caixa do negócio" com o "bolso do dono", estabelecer módica retirada para os sócios (pró-labore) | F58: Até 8% | G58: Enxugar estruturas e reduzir custos e despesas, não confundir faturamento com lucro, não misturar o "caixa do negócio" com o "bolso do dono", estabelecer módica retirada para os sócios (pró-labore)
B59: Entre 5 e 8% | C59: Revisar estruturas para identificar necessidade de enxugamento, revisar e acompanhar custos e despesas, principalmente juros de antecipação de faturas de cartão de crédito, pagamentos em atraso, empréstimos, financiamentos, outras dívidas | D59: Entre 3 e 6% | E59: Revisar estruturas para identificar necessidade de enxugamento, revisar e acompanhar custos e despesas, principalmente juros de antecipação de faturas de cartão de crédito, pagamentos em atraso, empréstimos, financiamentos, outras dívidas | F59: Entre 8 e 12% | G59: Revisar estruturas para identificar necessidade de enxugamento, revisar e acompanhar custos e despesas, principalmente juros de antecipação de faturas de cartão de crédito, pagamentos em atraso, empréstimos, financiamentos, outras dívidas
B60: Acima de 8% | C60: Acompanhar os números com vistas a melhorar a margem atual | D60: Acima de 6% | E60: Acompanhar os números com vistas a melhorar a margem atual | F60: Acima de 12% | G60: Acompanhar os números com vistas a melhorar a margem atual
A62: Relação Dívida Líquida / Ebitda | B62: até 2 | C62: Manter acompanhamento do nível de endividamento saudável | D62: até 2 | E62: Manter acompanhamento do nível de endividamento saudável | F62: até 2 | G62: Manter acompanhamento do nível de endividamento saudável
B63: entre 2 e 3 | C63: Evitar empréstimos de curto prazo e juros elevados | D63: entre 2 e 3 | E63: Evitar empréstimos de curto prazo e juros elevados | F63: entre 2 e 3 | G63: Evitar empréstimos de curto prazo e juros elevados
B64: acima de 3 | C64: Reduzir endividamento, não realizar antecipação de faturas de cartão de crédito, desconto de cheques e duplicatas, não recorrer a agiotas. Para investimentos efetivamente indispensáveis, obter recursos de longo prazo a juros subsidiados. Fugir de empréstimos de curto prazo e juros elevados, imobilizar somente o indispensável, postergar investimentos | D64: acima de 3 | E64: Reduzir endividamento, não realizar antecipação de faturas de cartão de crédito, desconto de cheques e duplicatas, não recorrer a agiotas. Para investimentos efetivamente indispensáveis, obter recursos de longo prazo a juros subsidiados. Fugir de empréstimos de curto prazo e juros elevados, imobilizar somente o indispensável, postergar investimentos | F64: acima de 3 | G64: Reduzir endividamento, não realizar antecipação de faturas de cartão de crédito, desconto de cheques e duplicatas, não recorrer a agiotas. Para investimentos efetivamente indispensáveis, obter recursos de longo prazo a juros subsidiados. Fugir de empréstimos de curto prazo e juros elevados, imobilizar somente o indispensável, postergar investimentos
A66: Relação Despesas Financeiras e EBITDA | B66: Até 35% | C66: Acompanhar com rigor as despesas financeiras em face de antecipação de faturas de cartão de crédito, desconto de cheques e duplicatas, empréstimos e financiamentos | D66: Até 20% | E66: Acompanhar com rigor as despesas financeiras em face de antecipação de faturas de cartão de crédito, desconto de cheques e duplicatas, empréstimos e financiamentos | F66: Até 30% | G66: Acompanhar com rigor as despesas financeiras em face de antecipação de faturas de cartão de crédito, desconto de cheques e duplicatas, empréstimos e financiamentos
B67: Entre 35 e 50% | C67: Evitar antecipação de faturas de cartão de crédito, desconto de cheques e duplicatas, bem como empréstimos de curto prazo e juros elevados, monitorar o crescimento das despesas financeiras | D67: Entre 20 e 40% | E67: Evitar antecipação de faturas de cartão de crédito, desconto de cheques e duplicatas, bem como empréstimos de curto prazo e juros elevados, monitorar o crescimento das despesas financeiras | F67: Entre 30 e 50% | G67: Evitar antecipação de faturas de cartão de crédito, desconto de cheques e duplicatas, bem como empréstimos de curto prazo e juros elevados, monitorar o crescimento das despesas financeiras
B68: Acima de 50% | C68: Reduzir as Despesas Financeiras, não realizar antecipação de faturas de cartão de crédito, desconto de cheques e duplicatas, não recorrer a agiotas. Para investimentos efetivamente indispensáveis, obter recursos de longo prazo a juros subsidiados. Fugir de empréstimos de curto prazo e juros elevados, imobilizar somente o indispensável, postergar investimentos | D68: Acima de 40% | E68: Reduzir as Despesas Financeiras, não realizar antecipação de faturas de cartão de crédito, desconto de cheques e duplicatas, não recorrer a agiotas. Para investimentos efetivamente indispensáveis, obter recursos de longo prazo a juros subsidiados. Fugir de empréstimos de curto prazo e juros elevados, imobilizar somente o indispensável, postergar investimentos | F68: Acima de 50% | G68: Reduzir as Despesas Financeiras, não realizar antecipação de faturas de cartão de crédito, desconto de cheques e duplicatas, não recorrer a agiotas. Para investimentos efetivamente indispensáveis, obter recursos de longo prazo a juros subsidiados. Fugir de empréstimos de curto prazo e juros elevados, imobilizar somente o indispensável, postergar investimentos
A70: Relação entre as Fontes de Recursos (RFR) | B70: Até 0,5 | C70: Acompanhar com rigor as despesas financeiras com antecipação de faturas de cartão de crédito, desconto de cheques e duplicatas, empréstimos, financiamentos e outras dívidas | D70: Até 0,5 | E70: Acompanhar com rigor as despesas financeiras com antecipação de faturas de cartão de crédito, desconto de cheques e duplicatas, empréstimos, financiamentos e outras dívidas | F70: Até 0,5 | G70: Acompanhar com rigor as despesas financeiras com antecipação de faturas de cartão de crédito, desconto de cheques e duplicatas, empréstimos, financiamentos e outras dívidas
B71: Entre 0,5 e 1 | C71: Evitar antecipação de faturas de cartão de crédito, desconto de cheques e duplicatas, empréstimos, financiamentos e outras dívidas | D71: Entre 0,5 e 1 | E71: Evitar antecipação de faturas de cartão de crédito, desconto de cheques e duplicatas, empréstimos, financiamentos e outras dívidas | F71: Entre 0,5 e 1 | G71: Evitar antecipação de faturas de cartão de crédito, desconto de cheques e duplicatas, empréstimos, financiamentos e outras dívidas
B72: Acima de 1 | C72: Reduzir o endividamento, identificar eventuais ativos não operacionais, redundantes, subutilizados, sucateados e ou não essenciais que possam ser monetizados e transformados em Capital de Giro Próprio (CDG), reduzir o volume de recursos de terceiros aplicados no negócio, imobilizar somente o indispensável, postergar investimentos | D72: Acima de 1 | E72: Reduzir o endividamento, identificar eventuais ativos não operacionais, redundantes, subutilizados, sucateados e ou não essenciais que possam ser monetizados e transformados em Capital de Giro Próprio (CDG), reduzir o volume de recursos de terceiros aplicados no negócio, imobilizar somente o indispensável, postergar investimentos | F72: Acima de 1 | G72: Reduzir o endividamento, identificar eventuais ativos não operacionais, redundantes, subutilizados, sucateados e ou não essenciais que possam ser monetizados e transformados em Capital de Giro Próprio (CDG), reduzir o volume de recursos de terceiros aplicados no negócio, imobilizar somente o indispensável, postergar investimentos
A74: Giro do Ativo (GA) | B74: Até 1 | C74: Gerenciar estoques para manter somente o mínimo necessário (just in time), aumentar a participação no mercado e a carteira de clientes, ajustar o volume de pedido e compras com as vendas, prazos de pagamento das compras e de recebimento dos clientes | D74: Até 2 | E74: Gerenciar estoques para manter somente o mínimo necessário (just in time), aumentar a participação no mercado e a carteira de clientes, ajustar o volume de pedido e compras com as vendas, prazos de pagamento das compras e de recebimento dos clientes | F74: Até 2 | G74: Aumentar a participação no mercado e a carteira de clientes, ajustar prazos de pagamento das compras e de recebimento dos clientes
B75: Entre 1 e 2 | C75: Gerenciar estoques para manter somente o mínimo necessário (just in time) | D75: Entre 2 e 3 | E75: Gerenciar estoques para manter somente o mínimo necessário (just in time) | F75: Entre 2 e 3 | G75: Acompanhar os números com vistas a melhorar a performace
B76: Acima de 2 | C76: Acompanhar diariamente o nível de estoques | D76: Acima de 3 | E76: Acompanhar diariamente o nível de estoques | F76: Acima de 3 | G76: Manter e melhorar a performace
A78: Prazo Médio de Pagamento das Compras (PMC) | B78: Até 30 dias | C78: Aumentar, de imediato, os prazos para pagamento das compras a fornecedores, ajustar pepdidos, compras, estoques e nível de vendas | D78: Até 30 dias | E78: Aumentar, de imediato, os prazos para pagamento das compras a fornecedores, ajustar pepdidos, compras, estoques e nível de vendas | F78: Até 30 dias | G78: Aumentar prazo para pagamento a fornecedores e nível com o nível de vendas
B79: Entre 30 e 60 | C79: Pugnar pelo aumento dos prazos para pagamento das compras a fornecedores | D79: Entre 30 e 60 | E79: Pugnar pelo aumento dos prazos para pagamento das compras a fornecedores | F79: Entre 30 e 60 | G79: Pugnar pelo aumento dos prazos para pagamento das compras a fornecedores
B80: Acima de 60 | C80: Acompanhar os pedidos, compras, estoques e nível de vendas | D80: Acima de 60 | E80: Acompanhar os pedidos, compras, estoques e nível de vendas | F80: Acima de 60 | G80: Acompanhar compras e nível de vendas
A83: Prazo Médio de Permanência dos Estoques (PME) | B83: Até 30 dias | C83: Acompanhar a gestão do estoque e avaliar as estratégias implantadas para aumento da rotação das mercadorias dos estoques | D83: Até 30 dias | E83: Acompanhar a gestão do estoque e avaliar as estratégias implantadas para aumento da rotação das mercadorias dos estoques | F83: Até 30 dias
B84: Entre 30 e 60 | C84: Gerenciar o estoque, ampliar a carteira de clientes e aumentar a participação no mercado, | D84: Entre 30 e 60 | E84: Gerenciar o estoque, ampliar a carteira de clientes e aumentar a participação no mercado, | F84: Entre 30 e 60
B85: Acima de 60 | C85: Gerenciar o estoque para manter somente o mínimo necessário (just in time), ampliar a carteira de clientes e aumentar a participação no mercado, implementar estratégias de aumento da rotação das mercadorias dos estoques | D85: Acima de 60 | E85: Gerenciar o estoque para manter somente o mínimo necessário (just in time), ampliar a carteira de clientes e aumentar a participação no mercado, implementar estratégias de aumento da rotação das mercadorias dos estoques | F85: Acima de 60 | G85: ampliar a carteira de clientes e aumentar a participação no mercado
A87: Prazo Médio de Recebimento das Vendas (PMR) | B87: Até 30 dias | C87: Monitorar os prazos das vendas, pugnar para que sejam sempre o menor possível | D87: Até 30 dias | E87: Monitorar os prazos das vendas, pugnar para que sejam sempre o menor possível | F87: Até 30 dias | G87: Monitorar os prazos das vendas, pugnar para que sejam sempre o menor possível
B88: Entre 30 e 60 | C88: Ampliar a carteira de clientes, aumentar a participação no mercado, identificar possíveis alternativas de redução do prazo de recebimento das vendas | D88: Entre 30 e 60 | E88: Ampliar a carteira de clientes, aumentar a participação no mercado, identificar possíveis alternativas de redução do prazo de recebimento das vendas | F88: Entre 30 e 60 | G88: Ampliar a carteira de clientes, aumentar a participação no mercado, identificar possíveis alternativas de redução do prazo de recebimento das vendas
B89: Acima de 60 | C89: Vender com os menores prazos, ampliar a carteira de clientes, aumentar a participação no mercado, implementar, com urgência, estratégias eficazes para redução do prazo de recebimento das vendas | D89: Acima de 60 | E89: Vender com os menores prazos, ampliar a carteira de clientes, aumentar a participação no mercado, implementar, com urgência, estratégias eficazes para redução do prazo de recebimento das vendas | F89: Acima de 60 | G89: Vender com os menores prazos, ampliar a carteira de clientes, aumentar a participação no mercado, implementar, com urgência, estratégias eficazes para redução do prazo de recebimento das vendas
A91: Inadimplência de Clientes | B91: até 3% | C91: Manter-se muito atento à gestão da carteira de cobrança de recebíveis | D91: até 3% | E91: Manter-se muito atento à gestão da carteira de cobrança de recebíveis | F91: até 3% | G91: Manter-se muito atento à gestão da carteira de cobrança de recebíveis
B92: entre 3 e 5% | C92: Revisar condições, premissas, parâmetros e procedimentos de análise de crédito para venda a prazo, e acompanhar com rigor a carteira de cobrança | D92: entre 3 e 5% | E92: Revisar condições, premissas, parâmetros e procedimentos de análise de crédito para venda a prazo, e acompanhar com rigor a carteira de cobrança | F92: entre 3 e 5% | G92: Revisar condições, premissas, parâmetros e procedimentos de análise de crédito para venda a prazo, e acompanhar com rigor a carteira de cobrança
B93: acima de 5% | C93: Vender somente à vista para clientes que se tornaram adimplentes e recalibrar a política de vendas a prazo, análise de crédito e intensificar a cobrança e negociação com vistas a receber as dívidas em atraso no menor prazo possível | D93: acima de 5% | E93: Vender somente à vista para clientes que se tornaram adimplentes e recalibrar a política de vendas a prazo, análise de crédito e intensificar a cobrança e negociação com vistas a receber as dívidas em atraso no menor prazo possível | F93: acima de 5% | G93: Vender somente à vista para clientes que se tornaram adimplentes e recalibrar a política de vendas a prazo, análise de crédito e intensificar a cobrança e negociação com vistas a receber as dívidas em atraso no menor prazo possível
A95: Ciclo Financeiro (CF) | B95: Até 30 dias | C95: Acompanhar os prazos para pagamento das compras a fornecedores e recebimento das vendas, e a rotação das mercadorias dos estoques | D95: Até 30 dias | E95: Acompanhar os prazos para pagamento das compras a fornecedores e recebimento das vendas, e a rotação das mercadorias dos estoques | F95: Até 30 dias | G95: Acompanhar os prazos para pagamento das compras a fornecedores e recebimento das vendas
B96: Entre 30 e 60 | C96: Pugnar pelo aumento dos prazos para pagamento das compras a fornecedores, identificar possíveis alternativas de redução do prazo de recebimento das vendas, implementar estratégias de aumento da rotação das mercadorias dos estoques; reduzir o descasamento das contas a pagar e a receber | D96: Entre 30 e 60 | E96: Pugnar pelo aumento dos prazos para pagamento das compras a fornecedores, identificar possíveis alternativas de redução do prazo de recebimento das vendas, implementar estratégias de aumento da rotação das mercadorias dos estoques; reduzir o descasamento das contas a pagar e a receber | F96: Entre 30 e 60 | G96: Pugnar pelo aumento dos prazos para pagamento das compras a fornecedores, identificar possíveis alternativas de redução do prazo de recebimento das vendas, reduzir o descasamento das contas a pagar e a receber
B97: Acima de 60 | C97: Vender com os menores prazos, ampliar a carteira de clientes e aumentar a participação no mercado, aumentr os prazos para pagamento das compras a fornecedores, reduzir o prazo de recebimento das vendas, implementar estratégias de aumento da rotação das mercadorias dos estoques, reduzir o descasamento das contas a pagar e a receber | D97: Acima de 60 | E97: Vender com os menores prazos, ampliar a carteira de clientes e aumentar a participação no mercado, aumentr os prazos para pagamento das compras a fornecedores, reduzir o prazo de recebimento das vendas, implementar estratégias de aumento da rotação das mercadorias dos estoques, reduzir o descasamento das contas a pagar e a receber | F97: Acima de 60 | G97: Vender com os menores prazos, ampliar a carteira de clientes e aumentar a participação no mercado, aumentr os prazos para pagamento das compras a fornecedores, reduzir o prazo de recebimento das vendas, reduzir o descasamento das contas a pagar e a receber
A99: Relação NCG/Vendas | B99: se negativo | C99: Pode indicar que a empresa não necessita de recursos para o giro de seus negócios. NCG negativa significa Investimento Operacional em Giro (IOG) | D99: se negativo | E99: Pode indicar que a empresa não necessita de recursos para o giro de seus negócios. NCG negativa significa Investimento Operacional em Giro (IOG) | F99: se negativo | G99: Pode indicar que a empresa não necessita de recursos para o giro de seus negócios. NCG negativa significa Investimento Operacional em Giro (IOG)
B100: até 10% | C100: Manter-se alerta às vendas a prazo, acompanhar o crescimento da rentabilidade e disponibilidade de capital de giro suficiente (recursos próprios) para financiar as vendas a prazo, para que não venha a causar insolvência. | D100: até 10% | E100: Manter-se alerta às vendas a prazo, acompanhar o crescimento da rentabilidade e disponibilidade de capital de giro suficiente (recursos próprios) para financiar as vendas a prazo, para que não venha a causar insolvência. | F100: até 10% | G100: Manter-se alerta às vendas a prazo, acompanhar o crescimento da rentabilidade e disponibilidade de capital de giro suficiente (recursos próprios) para financiar as vendas a prazo, para que não venha a causar insolvência.
B101: acima de 10% | C101: Não é recomendável a elevação das atividades e da NCG, se não acompanhada na mesma proporção pelo aumento das fontes de financiamento de longo prazo. A constante dependência de empréstimos demonstra a insuficiência de capital próprio para financiar as vendas a prazo. | D101: acima de 10% | E101: Não é recomendável a elevação das atividades e da NCG, se não acompanhada na mesma proporção pelo aumento das fontes de financiamento de longo prazo. A constante dependência de empréstimos demonstra a insuficiência de capital próprio para financiar as vendas a prazo. | F101: acima de 10% | G101: Não é recomendável a elevação das atividades e da NCG, se não acompanhada na mesma proporção pelo aumento das fontes de financiamento de longo prazo. A constante dependência de empréstimos demonstra a insuficiência de capital próprio para financiar as vendas a prazo.

Sheet Assinatura
A1: ID, Usuário (CNPJ ou CPF)
A2: email
A3: senha vigente?
A4: Pagamento Assinatura (ddmmaa)
A5: DEF realizados (ddmmaa)
A10: ASSINATURA ANUAL
A11: Não parcelar
A12: "nenhum usuário vai pagar mais do que o valor que percebe"
A13: acesso do usuário para alimentar a entrada de dados somente após cadastro login (CPNJ/CPF, email, senha) e conferência do pagamento da assinatura, no prazo de validadde (até 12 meses após a data do pagamento)
A14: alerta responsabilidade assinante pela consistência das informações digitadas na Entrada de Dados
A17: SUGESTÕES DE VALOR
A18: 360
A19: 150
A20: se incrementar com gráficos, dar uma enfeitada, tirar a imagem de ser só um excel... 1/2 salario
A21: degustação 1 mês grátis
A31: PAGAMENTO
A32: Chave Pix | B32: 28.261.669/0001-56
A33: Dados Bancários | B33: Banco: 077
B34: Agência: 0001
B35: Conta: 28166130-8
B36: CNPJ: 28261669/0001/-56
B37: EB PARCERIAS LTDA

Sheet lista
A1: TO DO
A2: DOING
A3: DONE
